<galaxy>
	<star name="Sol" temp="100" x="0" y="0" size="1.0" numPlanets="0" numGasGiants="0" >
		<planet name="Sol-16" DIMID="16">
			<isKnown>false</isKnown>
			<fogColor>1.0,1.0,1.0</fogColor>
			<skyColor>0.8,0.94362885,0.47287798</skyColor>
			<gravitationalMultiplier>119</gravitationalMultiplier>
			<orbitalDistance>138</orbitalDistance>
			<orbitalPhi>3</orbitalPhi>
			<rotationalPeriod>14241</rotationalPeriod>
			<atmosphereDensity>157</atmosphereDensity>
			<biomeIds>minecraft:extreme_hills</biomeIds>
			<planet name="Sol-16: 0" DIMID="17">
				<isKnown>false</isKnown>
				<hasRings>true</hasRings>
				<ringColor>0.343131,0.98731637,1.0</ringColor>
				<fogColor>1.0,1.0,1.0</fogColor>
				<skyColor>0.343131,0.98731637,1.0</skyColor>
				<gravitationalMultiplier>60</gravitationalMultiplier>
				<orbitalDistance>124</orbitalDistance>
				<orbitalPhi>-1</orbitalPhi>
				<rotationalPeriod>111111</rotationalPeriod>
				<atmosphereDensity>31</atmosphereDensity>
				<biomeIds>biomesoplenty:highland,minecraft:smaller_extreme_hills,minecraft:jungle_hills,minecraft:mutated_plains,biomesoplenty:bamboo_forest</biomeIds>
			</planet>
			<planet name="Sol-16: 1" DIMID="18">
				<isKnown>false</isKnown>
				<fogColor>1.0,1.0,1.0</fogColor>
				<skyColor>0.27684015,0.9008719,1.0</skyColor>
				<gravitationalMultiplier>58</gravitationalMultiplier>
				<orbitalDistance>149</orbitalDistance>
				<orbitalPhi>2</orbitalPhi>
				<rotationalPeriod>116857</rotationalPeriod>
				<atmosphereDensity>36</atmosphereDensity>
				<biomeIds>biomesoplenty:overgrown_cliffs,biomesoplenty:quagmire,biomesoplenty:coral_reef,biomesoplenty:orchard,minecraft:mutated_mesa_clear_rock</biomeIds>
			</planet>
			<planet name="Sol-16: 2" DIMID="19">
				<isKnown>false</isKnown>
				<fogColor>1.0,1.0,1.0</fogColor>
				<skyColor>0.21348357,0.78910625,1.0</skyColor>
				<gravitationalMultiplier>36</gravitationalMultiplier>
				<orbitalDistance>150</orbitalDistance>
				<orbitalPhi>-6</orbitalPhi>
				<rotationalPeriod>514403</rotationalPeriod>
				<atmosphereDensity>27</atmosphereDensity>
				<biomeIds>minecraft:savanna_rock,biomesoplenty:bayou,biomesoplenty:chaparral,minecraft:mesa_rock,biomesoplenty:ominous_woods</biomeIds>
			</planet>
			<oceanBlock>minecraft:lava</oceanBlock>
		</planet>
		<planet name="Earth" DIMID="0" dimMapping="">
			<isKnown>true</isKnown>
			<fogColor>1.0,1.0,1.0</fogColor>
			<skyColor>1.0,1.0,1.0</skyColor>
			<gravitationalMultiplier>100</gravitationalMultiplier>
			<orbitalDistance>100</orbitalDistance>
			<orbitalPhi>0</orbitalPhi>
			<rotationalPeriod>24000</rotationalPeriod>
			<atmosphereDensity>100</atmosphereDensity>
			<planet name="Luna" DIMID="2">
				<isKnown>false</isKnown>
				<fogColor>1.0,1.0,1.0</fogColor>
				<skyColor>1.0,1.0,1.0</skyColor>
				<gravitationalMultiplier>16</gravitationalMultiplier>
				<orbitalDistance>150</orbitalDistance>
				<orbitalPhi>0</orbitalPhi>
				<rotationalPeriod>128000</rotationalPeriod>
				<atmosphereDensity>0</atmosphereDensity>
				<biomeIds>advancedrocketry:moon,advancedrocketry:moondark</biomeIds>
			</planet>
		</planet>
		<planet name="Sol-3" DIMID="3">
			<isKnown>false</isKnown>
			<GasGiant>true</GasGiant>
			<gas>nitrogen</gas>
			<gas>oxygen</gas>
			<gas>hydrogen</gas>
			<fogColor>1.0,1.0,1.0</fogColor>
			<skyColor>1.0,1.0,1.0</skyColor>
			<gravitationalMultiplier>130</gravitationalMultiplier>
			<orbitalDistance>200</orbitalDistance>
			<orbitalPhi>0</orbitalPhi>
			<rotationalPeriod>24000</rotationalPeriod>
			<atmosphereDensity>104</atmosphereDensity>
			<planet name="Sol-3: 0" DIMID="4">
				<isKnown>false</isKnown>
				<fogColor>1.0,1.0,1.0</fogColor>
				<skyColor>0.34118724,0.6904652,1.0</skyColor>
				<gravitationalMultiplier>63</gravitationalMultiplier>
				<orbitalDistance>121</orbitalDistance>
				<orbitalPhi>0</orbitalPhi>
				<rotationalPeriod>95981</rotationalPeriod>
				<atmosphereDensity>20</atmosphereDensity>
				<seaLevel>75</seaLevel>
				<biomeIds>advancedrocketry:moon,advancedrocketry:moondark</biomeIds>
				<oceanBlock>advancedrocketry:oxygenfluid</oceanBlock>
			</planet>
			<planet name="Sol-3: 1" DIMID="5">
				<isKnown>false</isKnown>
				<fogColor>1.0,1.0,1.0</fogColor>
				<skyColor>0.0,0.88922626,1.0</skyColor>
				<gravitationalMultiplier>86</gravitationalMultiplier>
				<orbitalDistance>198</orbitalDistance>
				<orbitalPhi>2</orbitalPhi>
				<rotationalPeriod>37732</rotationalPeriod>
				<atmosphereDensity>14</atmosphereDensity>
				<biomeIds>advancedrocketry:moon,advancedrocketry:moondark</biomeIds>
			</planet>
		</planet>
		<planet name="Sol-20" DIMID="20">
			<isKnown>false</isKnown>
			<fogColor>1.0,1.0,1.0</fogColor>
			<skyColor>0.51835245,0.74395186,1.0</skyColor>
			<gravitationalMultiplier>123</gravitationalMultiplier>
			<orbitalDistance>147</orbitalDistance>
			<orbitalPhi>-3</orbitalPhi>
			<rotationalPeriod>12897</rotationalPeriod>
			<atmosphereDensity>59</atmosphereDensity>
			<biomeIds>biomesoplenty:flower_island,biomesoplenty:marsh,biomesoplenty:redwood_forest_edge,minecraft:roofed_forest,advancedrocketry:oceanspires</biomeIds>
		</planet>
		<planet name="Sol-21" DIMID="21">
			<isKnown>false</isKnown>
			<fogColor>1.0,1.0,1.0</fogColor>
			<skyColor>0.77779144,0.7282994,1.0</skyColor>
			<gravitationalMultiplier>130</gravitationalMultiplier>
			<orbitalDistance>70</orbitalDistance>
			<orbitalPhi>-3</orbitalPhi>
			<rotationalPeriod>10923</rotationalPeriod>
			<atmosphereDensity>30</atmosphereDensity>
			<biomeIds>minecraft:mutated_redwood_taiga_hills,minecraft:mesa_rock,biomesoplenty:orchard,biomesoplenty:land_of_lakes,minecraft:mutated_redwood_taiga</biomeIds>
			<planet name="Sol-21: 0" DIMID="22">
				<isKnown>false</isKnown>
				<fogColor>1.0,1.0,1.0</fogColor>
				<skyColor>0.037085116,0.6854043,1.0</skyColor>
				<gravitationalMultiplier>56</gravitationalMultiplier>
				<orbitalDistance>180</orbitalDistance>
				<orbitalPhi>-2</orbitalPhi>
				<rotationalPeriod>136661</rotationalPeriod>
				<atmosphereDensity>35</atmosphereDensity>
				<biomeIds>biomesoplenty:visceral_heap,minecraft:forest_hills,biomesoplenty:flower_field,biomesoplenty:corrupted_sands,biomesoplenty:outback</biomeIds>
			</planet>
			<planet name="Sol-21: 1" DIMID="23">
				<isKnown>false</isKnown>
				<fogColor>1.0,1.0,1.0</fogColor>
				<skyColor>0.3191259,0.851413,1.0</skyColor>
				<gravitationalMultiplier>72</gravitationalMultiplier>
				<orbitalDistance>136</orbitalDistance>
				<orbitalPhi>3</orbitalPhi>
				<rotationalPeriod>64300</rotationalPeriod>
				<atmosphereDensity>37</atmosphereDensity>
				<biomeIds>biomesoplenty:bayou,minecraft:birch_forest,biomesoplenty:lush_desert,minecraft:savanna_rock,minecraft:mutated_savanna_rock</biomeIds>
			</planet>
			<planet name="Sol-21: 2" DIMID="24">
				<isKnown>false</isKnown>
				<fogColor>1.0,1.0,1.0</fogColor>
				<skyColor>0.44440794,0.6316501,1.0</skyColor>
				<gravitationalMultiplier>71</gravitationalMultiplier>
				<orbitalDistance>108</orbitalDistance>
				<orbitalPhi>-1</orbitalPhi>
				<rotationalPeriod>67055</rotationalPeriod>
				<atmosphereDensity>18</atmosphereDensity>
				<seaLevel>67</seaLevel>
				<biomeIds>advancedrocketry:moon,advancedrocketry:moondark</biomeIds>
			</planet>
		</planet>
		<planet name="Sol-6" DIMID="6">
			<isKnown>false</isKnown>
			<fogColor>1.0,1.0,1.0</fogColor>
			<skyColor>0.8,0.75444853,0.0</skyColor>
			<gravitationalMultiplier>94</gravitationalMultiplier>
			<orbitalDistance>92</orbitalDistance>
			<orbitalPhi>0</orbitalPhi>
			<rotationalPeriod>28895</rotationalPeriod>
			<atmosphereDensity>200</atmosphereDensity>
			<biomeIds>advancedrocketry:hotdryrock,advancedrocketry:volcanic</biomeIds>
			<oceanBlock>minecraft:lava</oceanBlock>
		</planet>
		<planet name="Sol-7" DIMID="7">
			<isKnown>false</isKnown>
			<fogColor>1.0,1.0,1.0</fogColor>
			<skyColor>0.8,0.85139203,0.97376186</skyColor>
			<gravitationalMultiplier>93</gravitationalMultiplier>
			<orbitalDistance>139</orbitalDistance>
			<orbitalPhi>-2</orbitalPhi>
			<rotationalPeriod>29837</rotationalPeriod>
			<atmosphereDensity>108</atmosphereDensity>
			<biomeIds>biomesoplenty:pasture,biomesoplenty:mountain_foothills,biomesoplenty:fen,biomesoplenty:shield,minecraft:forest</biomeIds>
		</planet>
		<planet name="Sol-8" DIMID="8">
			<isKnown>false</isKnown>
			<fogColor>1.0,1.0,1.0</fogColor>
			<skyColor>0.3170566,0.9262615,1.0</skyColor>
			<gravitationalMultiplier>116</gravitationalMultiplier>
			<orbitalDistance>160</orbitalDistance>
			<orbitalPhi>-5</orbitalPhi>
			<rotationalPeriod>14984</rotationalPeriod>
			<atmosphereDensity>51</atmosphereDensity>
			<biomeIds>biomesoplenty:temperate_rainforest,minecraft:extreme_hills_with_trees,biomesoplenty:coral_reef,biomesoplenty:redwood_forest_edge,biomesoplenty:highland</biomeIds>
			<planet name="Sol-8: 0" DIMID="9">
				<isKnown>false</isKnown>
				<fogColor>1.0,1.0,1.0</fogColor>
				<skyColor>0.2656992,0.67420304,1.0</skyColor>
				<gravitationalMultiplier>66</gravitationalMultiplier>
				<orbitalDistance>129</orbitalDistance>
				<orbitalPhi>-1</orbitalPhi>
				<rotationalPeriod>83479</rotationalPeriod>
				<atmosphereDensity>23</atmosphereDensity>
				<biomeIds>advancedrocketry:moon,advancedrocketry:moondark</biomeIds>
			</planet>
		</planet>
		<planet name="Sol-10" DIMID="10">
			<isKnown>false</isKnown>
			<fogColor>1.0,1.0,1.0</fogColor>
			<skyColor>0.8,0.68689704,0.10657573</skyColor>
			<gravitationalMultiplier>115</gravitationalMultiplier>
			<orbitalDistance>108</orbitalDistance>
			<orbitalPhi>-2</orbitalPhi>
			<rotationalPeriod>15780</rotationalPeriod>
			<atmosphereDensity>178</atmosphereDensity>
			<biomeIds>advancedrocketry:hotdryrock,advancedrocketry:volcanic</biomeIds>
			<planet name="Sol-10: 0" DIMID="11">
				<isKnown>false</isKnown>
				<hasRings>true</hasRings>
				<ringColor>0.0,0.67499524,1.0</ringColor>
				<fogColor>1.0,1.0,1.0</fogColor>
				<skyColor>0.0,0.67499524,1.0</skyColor>
				<gravitationalMultiplier>51</gravitationalMultiplier>
				<orbitalDistance>182</orbitalDistance>
				<orbitalPhi>0</orbitalPhi>
				<rotationalPeriod>180925</rotationalPeriod>
				<atmosphereDensity>33</atmosphereDensity>
				<biomeIds>biomesoplenty:pasture,minecraft:birch_forest,biomesoplenty:outback,minecraft:mutated_plains,biomesoplenty:woodland</biomeIds>
			</planet>
			<oceanBlock>minecraft:lava</oceanBlock>
		</planet>
		<planet name="Sol-12" DIMID="12">
			<isKnown>false</isKnown>
			<fogColor>1.0,1.0,1.0</fogColor>
			<skyColor>0.8,0.95681405,0.6692929</skyColor>
			<gravitationalMultiplier>101</gravitationalMultiplier>
			<orbitalDistance>39</orbitalDistance>
			<orbitalPhi>-5</orbitalPhi>
			<rotationalPeriod>23294</rotationalPeriod>
			<atmosphereDensity>57</atmosphereDensity>
			<biomeIds>minecraft:mutated_swampland,biomesoplenty:lavender_fields,biomesoplenty:kelp_forest,biomesoplenty:woodland,biomesoplenty:white_beach</biomeIds>
			<planet name="Sol-12: 0" DIMID="13">
				<isKnown>false</isKnown>
				<fogColor>1.0,1.0,1.0</fogColor>
				<skyColor>0.27991873,0.82398975,1.0</skyColor>
				<gravitationalMultiplier>31</gravitationalMultiplier>
				<orbitalDistance>139</orbitalDistance>
				<orbitalPhi>2</orbitalPhi>
				<rotationalPeriod>805612</rotationalPeriod>
				<atmosphereDensity>24</atmosphereDensity>
				<biomeIds>advancedrocketry:moon,advancedrocketry:moondark</biomeIds>
			</planet>
			<planet name="Sol-12: 1" DIMID="14">
				<isKnown>false</isKnown>
				<fogColor>1.0,1.0,1.0</fogColor>
				<skyColor>0.41389847,0.58428603,1.0</skyColor>
				<gravitationalMultiplier>35</gravitationalMultiplier>
				<orbitalDistance>117</orbitalDistance>
				<orbitalPhi>-4</orbitalPhi>
				<rotationalPeriod>559766</rotationalPeriod>
				<atmosphereDensity>25</atmosphereDensity>
				<biomeIds>advancedrocketry:moon,advancedrocketry:moondark</biomeIds>
			</planet>
			<oceanBlock>minecraft:lava</oceanBlock>
		</planet>
		<planet name="Sol-15" DIMID="15">
			<isKnown>false</isKnown>
			<fogColor>1.0,1.0,1.0</fogColor>
			<skyColor>0.406384,0.7268617,1.0</skyColor>
			<gravitationalMultiplier>130</gravitationalMultiplier>
			<orbitalDistance>128</orbitalDistance>
			<orbitalPhi>-2</orbitalPhi>
			<rotationalPeriod>10923</rotationalPeriod>
			<atmosphereDensity>35</atmosphereDensity>
			<biomeIds>biomesoplenty:flower_island,biomesoplenty:oasis,biomesoplenty:kelp_forest,minecraft:mutated_redwood_taiga,minecraft:mutated_jungle_edge</biomeIds>
		</planet>
	</star>
	<star name="Wolf 12" temp="10" x="300" y="-200" size="1.0" numPlanets="0" numGasGiants="0" >
		<planet name="Sol-35" DIMID="35">
			<isKnown>false</isKnown>
			<fogColor>1.0,1.0,1.0</fogColor>
			<skyColor>0.8,0.97919226,0.3803442</skyColor>
			<gravitationalMultiplier>126</gravitationalMultiplier>
			<orbitalDistance>115</orbitalDistance>
			<orbitalPhi>0</orbitalPhi>
			<rotationalPeriod>11997</rotationalPeriod>
			<atmosphereDensity>150</atmosphereDensity>
			<biomeIds>biomesoplenty:shrubland,biomesoplenty:coral_reef,biomesoplenty:sacred_springs,biomesoplenty:temperate_rainforest,biomesoplenty:volcanic_island,advancedrocketry:deepswamp,advancedrocketry:stormland</biomeIds>
			<planet name="Sol-35: 0" DIMID="36">
				<isKnown>false</isKnown>
				<fogColor>1.0,1.0,1.0</fogColor>
				<skyColor>0.13971424,0.7867415,1.0</skyColor>
				<gravitationalMultiplier>73</gravitationalMultiplier>
				<orbitalDistance>151</orbitalDistance>
				<orbitalPhi>-3</orbitalPhi>
				<rotationalPeriod>61693</rotationalPeriod>
				<atmosphereDensity>34</atmosphereDensity>
				<seaLevel>78</seaLevel>
				<biomeIds>biomesoplenty:temperate_rainforest,biomesoplenty:highland,biomesoplenty:cherry_blossom_grove,advancedrocketry:marsh,biomesoplenty:quagmire</biomeIds>
			</planet>
			<planet name="Sol-35: 1" DIMID="37">
				<isKnown>false</isKnown>
				<fogColor>1.0,1.0,1.0</fogColor>
				<skyColor>0.41849488,0.92120683,1.0</skyColor>
				<gravitationalMultiplier>75</gravitationalMultiplier>
				<orbitalDistance>107</orbitalDistance>
				<orbitalPhi>4</orbitalPhi>
				<rotationalPeriod>56888</rotationalPeriod>
				<atmosphereDensity>19</atmosphereDensity>
				<biomeIds>advancedrocketry:moon,advancedrocketry:moondark</biomeIds>
			</planet>
			<oceanBlock>minecraft:lava</oceanBlock>
		</planet>
		<planet name="Sol-38" DIMID="38">
			<isKnown>false</isKnown>
			<fogColor>1.0,1.0,1.0</fogColor>
			<skyColor>0.8,0.55006516,0.8420215</skyColor>
			<gravitationalMultiplier>109</gravitationalMultiplier>
			<orbitalDistance>95</orbitalDistance>
			<orbitalPhi>4</orbitalPhi>
			<rotationalPeriod>18532</rotationalPeriod>
			<atmosphereDensity>89</atmosphereDensity>
			<biomeIds>biomesoplenty:flower_field,biomesoplenty:fungi_forest,biomesoplenty:tropical_island,biomesoplenty:lush_desert,biomesoplenty:outback</biomeIds>
			<planet name="Sol-38: 0" DIMID="39">
				<isKnown>false</isKnown>
				<fogColor>1.0,1.0,1.0</fogColor>
				<skyColor>0.4767735,0.7276139,1.0</skyColor>
				<gravitationalMultiplier>65</gravitationalMultiplier>
				<orbitalDistance>110</orbitalDistance>
				<orbitalPhi>2</orbitalPhi>
				<rotationalPeriod>87391</rotationalPeriod>
				<atmosphereDensity>28</atmosphereDensity>
				<biomeIds>minecraft:roofed_forest,biomesoplenty:prairie,minecraft:beaches,biomesoplenty:mountain_foothills,minecraft:mutated_forest</biomeIds>
			</planet>
			<planet name="Sol-38: 1" DIMID="40">
				<isKnown>false</isKnown>
				<fogColor>1.0,1.0,1.0</fogColor>
				<skyColor>0.042598963,0.60268587,1.0</skyColor>
				<gravitationalMultiplier>71</gravitationalMultiplier>
				<orbitalDistance>151</orbitalDistance>
				<orbitalPhi>-5</orbitalPhi>
				<rotationalPeriod>67055</rotationalPeriod>
				<atmosphereDensity>19</atmosphereDensity>
				<biomeIds>advancedrocketry:moon,advancedrocketry:moondark</biomeIds>
			</planet>
		</planet>
		<planet name="Sol-25" DIMID="25">
			<isKnown>false</isKnown>
			<fogColor>1.0,1.0,1.0</fogColor>
			<skyColor>0.8,0.8742535,0.09338361</skyColor>
			<gravitationalMultiplier>116</gravitationalMultiplier>
			<orbitalDistance>61</orbitalDistance>
			<orbitalPhi>0</orbitalPhi>
			<rotationalPeriod>14984</rotationalPeriod>
			<atmosphereDensity>139</atmosphereDensity>
			<biomeIds>advancedrocketry:hotdryrock,advancedrocketry:volcanic</biomeIds>
			<planet name="Sol-25: 0" DIMID="26">
				<isKnown>false</isKnown>
				<fogColor>1.0,1.0,1.0</fogColor>
				<skyColor>0.38530076,0.5540827,1.0</skyColor>
				<gravitationalMultiplier>34</gravitationalMultiplier>
				<orbitalDistance>103</orbitalDistance>
				<orbitalPhi>0</orbitalPhi>
				<rotationalPeriod>610624</rotationalPeriod>
				<atmosphereDensity>20</atmosphereDensity>
				<biomeIds>advancedrocketry:moon,advancedrocketry:moondark</biomeIds>
			</planet>
			<oceanBlock>minecraft:lava</oceanBlock>
		</planet>
		<planet name="Sol-27" DIMID="27">
			<isKnown>false</isKnown>
			<fogColor>1.0,1.0,1.0</fogColor>
			<skyColor>0.8,0.8368411,0.9083255</skyColor>
			<gravitationalMultiplier>119</gravitationalMultiplier>
			<orbitalDistance>163</orbitalDistance>
			<orbitalPhi>-7</orbitalPhi>
			<rotationalPeriod>14241</rotationalPeriod>
			<atmosphereDensity>137</atmosphereDensity>
			<biomeIds>advancedrocketry:crystalchasms</biomeIds>
			<planet name="Sol-27: 0" DIMID="28">
				<isKnown>false</isKnown>
				<fogColor>1.0,1.0,1.0</fogColor>
				<skyColor>0.48391926,0.75357604,1.0</skyColor>
				<gravitationalMultiplier>44</gravitationalMultiplier>
				<orbitalDistance>109</orbitalDistance>
				<orbitalPhi>0</orbitalPhi>
				<rotationalPeriod>281743</rotationalPeriod>
				<atmosphereDensity>34</atmosphereDensity>
				<biomeIds>biomesoplenty:mangrove,minecraft:extreme_hills,biomesoplenty:xeric_shrubland,biomesoplenty:sacred_springs,biomesoplenty:temperate_rainforest</biomeIds>
			</planet>
			<planet name="Sol-27: 1" DIMID="29">
				<isKnown>false</isKnown>
				<fogColor>1.0,1.0,1.0</fogColor>
				<skyColor>0.0,0.9258615,1.0</skyColor>
				<gravitationalMultiplier>36</gravitationalMultiplier>
				<orbitalDistance>188</orbitalDistance>
				<orbitalPhi>0</orbitalPhi>
				<rotationalPeriod>514403</rotationalPeriod>
				<atmosphereDensity>28</atmosphereDensity>
				<biomeIds>minecraft:mutated_birch_forest,minecraft:forest_hills,minecraft:savanna_rock,biomesoplenty:shrubland,biomesoplenty:orchard</biomeIds>
			</planet>
			<planet name="Sol-27: 2" DIMID="30">
				<isKnown>false</isKnown>
				<fogColor>1.0,1.0,1.0</fogColor>
				<skyColor>0.22433746,0.59894145,1.0</skyColor>
				<gravitationalMultiplier>69</gravitationalMultiplier>
				<orbitalDistance>140</orbitalDistance>
				<orbitalPhi>-2</orbitalPhi>
				<rotationalPeriod>73057</rotationalPeriod>
				<atmosphereDensity>36</atmosphereDensity>
				<biomeIds>advancedrocketry:oceanspires,minecraft:savanna_rock,biomesoplenty:rainforest,biomesoplenty:shrubland,biomesoplenty:land_of_lakes</biomeIds>
			</planet>
		</planet>
		<planet name="Sol-31" DIMID="31">
			<isKnown>false</isKnown>
			<fogColor>1.0,1.0,1.0</fogColor>
			<skyColor>0.25514114,0.6622678,1.0</skyColor>
			<gravitationalMultiplier>125</gravitationalMultiplier>
			<orbitalDistance>174</orbitalDistance>
			<orbitalPhi>-8</orbitalPhi>
			<rotationalPeriod>12288</rotationalPeriod>
			<atmosphereDensity>58</atmosphereDensity>
			<biomeIds>biomesoplenty:flower_field,biomesoplenty:gravel_beach,biomesoplenty:oasis,biomesoplenty:white_beach,minecraft:forest_hills</biomeIds>
			<planet name="Sol-31: 0" DIMID="32">
				<isKnown>false</isKnown>
				<fogColor>1.0,1.0,1.0</fogColor>
				<skyColor>0.28680307,0.6906485,1.0</skyColor>
				<gravitationalMultiplier>70</gravitationalMultiplier>
				<orbitalDistance>136</orbitalDistance>
				<orbitalPhi>4</orbitalPhi>
				<rotationalPeriod>69970</rotationalPeriod>
				<atmosphereDensity>33</atmosphereDensity>
				<biomeIds>biomesoplenty:land_of_lakes,biomesoplenty:bayou,minecraft:savanna,biomesoplenty:grove,minecraft:forest_hills</biomeIds>
			</planet>
			<planet name="Sol-31: 1" DIMID="33">
				<isKnown>false</isKnown>
				<fogColor>1.0,1.0,1.0</fogColor>
				<skyColor>0.0,0.7896699,1.0</skyColor>
				<gravitationalMultiplier>52</gravitationalMultiplier>
				<orbitalDistance>197</orbitalDistance>
				<orbitalPhi>-3</orbitalPhi>
				<rotationalPeriod>161206</rotationalPeriod>
				<atmosphereDensity>30</atmosphereDensity>
				<seaLevel>56</seaLevel>
				<biomeIds>biomesoplenty:mountain_foothills,biomesoplenty:eucalyptus_forest,minecraft:mutated_roofed_forest,biomesoplenty:bayou,biomesoplenty:volcanic_island</biomeIds>
			</planet>
			<planet name="Sol-31: 2" DIMID="34">
				<isKnown>false</isKnown>
				<fogColor>1.0,1.0,1.0</fogColor>
				<skyColor>0.14429939,0.8449993,1.0</skyColor>
				<gravitationalMultiplier>65</gravitationalMultiplier>
				<orbitalDistance>145</orbitalDistance>
				<orbitalPhi>-4</orbitalPhi>
				<rotationalPeriod>87391</rotationalPeriod>
				<atmosphereDensity>28</atmosphereDensity>
				<biomeIds>biomesoplenty:white_beach,biomesoplenty:lush_swamp,minecraft:forest,biomesoplenty:redwood_forest,biomesoplenty:volcanic_island</biomeIds>
			</planet>
		</planet>
	</star>
	<star name="Epsilon ire" temp="170" x="-200" y="80" size="1.0" numPlanets="0" numGasGiants="0" >
		<planet name="Sol-49" DIMID="49">
			<isKnown>false</isKnown>
			<fogColor>1.0,1.0,1.0</fogColor>
			<skyColor>0.8,0.5575402,0.7671099</skyColor>
			<gravitationalMultiplier>130</gravitationalMultiplier>
			<orbitalDistance>149</orbitalDistance>
			<orbitalPhi>-2</orbitalPhi>
			<rotationalPeriod>10923</rotationalPeriod>
			<atmosphereDensity>134</atmosphereDensity>
			<seaLevel>75</seaLevel>
			<biomeIds>biomesoplenty:mountain,minecraft:desert,minecraft:mutated_extreme_hills,minecraft:mutated_swampland,minecraft:deep_ocean,advancedrocketry:deepswamp,advancedrocketry:stormland</biomeIds>
			<planet name="Sol-49: 0" DIMID="50">
				<isKnown>false</isKnown>
				<fogColor>1.0,1.0,1.0</fogColor>
				<skyColor>0.0,0.5789404,1.0</skyColor>
				<gravitationalMultiplier>62</gravitationalMultiplier>
				<orbitalDistance>196</orbitalDistance>
				<orbitalPhi>1</orbitalPhi>
				<rotationalPeriod>100701</rotationalPeriod>
				<atmosphereDensity>20</atmosphereDensity>
				<biomeIds>advancedrocketry:moon,advancedrocketry:moondark</biomeIds>
			</planet>
		</planet>
		<planet name="Sol-51" DIMID="51">
			<isKnown>false</isKnown>
			<fogColor>1.0,1.0,1.0</fogColor>
			<skyColor>0.8,0.6862791,0.285855</skyColor>
			<gravitationalMultiplier>120</gravitationalMultiplier>
			<orbitalDistance>88</orbitalDistance>
			<orbitalPhi>-1</orbitalPhi>
			<rotationalPeriod>13888</rotationalPeriod>
			<atmosphereDensity>136</atmosphereDensity>
			<biomeIds>minecraft:mushroom_island</biomeIds>
			<oceanBlock>minecraft:lava</oceanBlock>
		</planet>
		<planet name="Sol-52" DIMID="52">
			<isKnown>false</isKnown>
			<fogColor>1.0,1.0,1.0</fogColor>
			<skyColor>0.7864623,0.9262601,1.0</skyColor>
			<gravitationalMultiplier>130</gravitationalMultiplier>
			<orbitalDistance>92</orbitalDistance>
			<orbitalPhi>0</orbitalPhi>
			<rotationalPeriod>10923</rotationalPeriod>
			<atmosphereDensity>39</atmosphereDensity>
			<biomeIds>biomesoplenty:ominous_woods,minecraft:mutated_extreme_hills_with_trees,minecraft:mushroom_island,biomesoplenty:brushland,minecraft:jungle_hills</biomeIds>
			<planet name="Sol-52: 0" DIMID="53">
				<isKnown>false</isKnown>
				<fogColor>1.0,1.0,1.0</fogColor>
				<skyColor>0.0,0.6363343,1.0</skyColor>
				<gravitationalMultiplier>45</gravitationalMultiplier>
				<orbitalDistance>200</orbitalDistance>
				<orbitalPhi>0</orbitalPhi>
				<rotationalPeriod>263374</rotationalPeriod>
				<atmosphereDensity>25</atmosphereDensity>
				<seaLevel>75</seaLevel>
				<biomeIds>advancedrocketry:moon,advancedrocketry:moondark</biomeIds>
				<oceanBlock>advancedrocketry:oxygenfluid</oceanBlock>
			</planet>
			<planet name="Sol-52: 1" DIMID="54">
				<isKnown>false</isKnown>
				<fogColor>1.0,1.0,1.0</fogColor>
				<skyColor>0.39528883,0.63488305,1.0</skyColor>
				<gravitationalMultiplier>45</gravitationalMultiplier>
				<orbitalDistance>109</orbitalDistance>
				<orbitalPhi>0</orbitalPhi>
				<rotationalPeriod>263374</rotationalPeriod>
				<atmosphereDensity>20</atmosphereDensity>
				<biomeIds>advancedrocketry:moon,advancedrocketry:moondark</biomeIds>
			</planet>
			<planet name="Sol-52: 2" DIMID="55">
				<isKnown>false</isKnown>
				<fogColor>1.0,1.0,1.0</fogColor>
				<skyColor>0.29254258,0.64536524,1.0</skyColor>
				<gravitationalMultiplier>81</gravitationalMultiplier>
				<orbitalDistance>127</orbitalDistance>
				<orbitalPhi>-2</orbitalPhi>
				<rotationalPeriod>45160</rotationalPeriod>
				<atmosphereDensity>21</atmosphereDensity>
				<seaLevel>66</seaLevel>
				<biomeIds>advancedrocketry:moon,advancedrocketry:moondark</biomeIds>
			</planet>
		</planet>
		<planet name="Sol-56" DIMID="56">
			<isKnown>false</isKnown>
			<fogColor>1.0,1.0,1.0</fogColor>
			<skyColor>0.8,0.696355,0.0</skyColor>
			<gravitationalMultiplier>116</gravitationalMultiplier>
			<orbitalDistance>128</orbitalDistance>
			<orbitalPhi>0</orbitalPhi>
			<rotationalPeriod>14984</rotationalPeriod>
			<atmosphereDensity>200</atmosphereDensity>
			<biomeIds>advancedrocketry:hotdryrock,advancedrocketry:volcanic</biomeIds>
			<planet name="Sol-56: 0" DIMID="57">
				<isKnown>false</isKnown>
				<fogColor>1.0,1.0,1.0</fogColor>
				<skyColor>0.3117919,0.7864305,1.0</skyColor>
				<gravitationalMultiplier>66</gravitationalMultiplier>
				<orbitalDistance>133</orbitalDistance>
				<orbitalPhi>1</orbitalPhi>
				<rotationalPeriod>83479</rotationalPeriod>
				<atmosphereDensity>24</atmosphereDensity>
				<biomeIds>advancedrocketry:moon,advancedrocketry:moondark</biomeIds>
			</planet>
			<oceanBlock>minecraft:lava</oceanBlock>
		</planet>
		<planet name="Sol-41" DIMID="41">
			<isKnown>false</isKnown>
			<fogColor>1.0,1.0,1.0</fogColor>
			<skyColor>0.8,0.82405484,0.0</skyColor>
			<gravitationalMultiplier>130</gravitationalMultiplier>
			<orbitalDistance>15</orbitalDistance>
			<orbitalPhi>2</orbitalPhi>
			<rotationalPeriod>10923</rotationalPeriod>
			<atmosphereDensity>162</atmosphereDensity>
			<biomeIds>advancedrocketry:hotdryrock,advancedrocketry:volcanic</biomeIds>
			<planet name="Sol-41: 0" DIMID="42">
				<isKnown>false</isKnown>
				<fogColor>1.0,1.0,1.0</fogColor>
				<skyColor>0.3702591,0.92878926,1.0</skyColor>
				<gravitationalMultiplier>76</gravitationalMultiplier>
				<orbitalDistance>113</orbitalDistance>
				<orbitalPhi>0</orbitalPhi>
				<rotationalPeriod>54672</rotationalPeriod>
				<atmosphereDensity>19</atmosphereDensity>
				<biomeIds>advancedrocketry:moon,advancedrocketry:moondark</biomeIds>
			</planet>
			<oceanBlock>minecraft:lava</oceanBlock>
		</planet>
		<planet name="Sol-43" DIMID="43">
			<isKnown>false</isKnown>
			<fogColor>1.0,1.0,1.0</fogColor>
			<skyColor>0.8,0.5836112,0.15349114</skyColor>
			<gravitationalMultiplier>130</gravitationalMultiplier>
			<orbitalDistance>82</orbitalDistance>
			<orbitalPhi>-3</orbitalPhi>
			<rotationalPeriod>10923</rotationalPeriod>
			<atmosphereDensity>144</atmosphereDensity>
			<biomeIds>advancedrocketry:hotdryrock,advancedrocketry:volcanic</biomeIds>
			<planet name="Sol-43: 0" DIMID="44">
				<isKnown>false</isKnown>
				<fogColor>1.0,1.0,1.0</fogColor>
				<skyColor>0.16353804,0.56747127,1.0</skyColor>
				<gravitationalMultiplier>60</gravitationalMultiplier>
				<orbitalDistance>160</orbitalDistance>
				<orbitalPhi>2</orbitalPhi>
				<rotationalPeriod>111111</rotationalPeriod>
				<atmosphereDensity>31</atmosphereDensity>
				<biomeIds>biomesoplenty:white_beach,biomesoplenty:mountain_foothills,biomesoplenty:visceral_heap,biomesoplenty:wetland,minecraft:mutated_mesa_clear_rock</biomeIds>
			</planet>
			<oceanBlock>minecraft:lava</oceanBlock>
		</planet>
		<planet name="Sol-45" DIMID="45">
			<isKnown>false</isKnown>
			<hasRings>true</hasRings>
			<ringColor>0.21096426,0.9495981,1.0</ringColor>
			<fogColor>1.0,1.0,1.0</fogColor>
			<skyColor>0.21096426,0.9495981,1.0</skyColor>
			<gravitationalMultiplier>104</gravitationalMultiplier>
			<orbitalDistance>200</orbitalDistance>
			<orbitalPhi>-4</orbitalPhi>
			<rotationalPeriod>21335</rotationalPeriod>
			<atmosphereDensity>75</atmosphereDensity>
			<biomeIds>biomesoplenty:mountain,minecraft:jungle_edge,biomesoplenty:outback,biomesoplenty:grove,advancedrocketry:oceanspires</biomeIds>
			<planet name="Sol-45: 2" DIMID="48">
				<isKnown>false</isKnown>
				<fogColor>1.0,1.0,1.0</fogColor>
				<skyColor>0.041447222,0.906315,1.0</skyColor>
				<gravitationalMultiplier>75</gravitationalMultiplier>
				<orbitalDistance>170</orbitalDistance>
				<orbitalPhi>-1</orbitalPhi>
				<rotationalPeriod>56888</rotationalPeriod>
				<atmosphereDensity>21</atmosphereDensity>
				<biomeIds>advancedrocketry:moon,advancedrocketry:moondark</biomeIds>
			</planet>
			<planet name="Sol-45: 0" DIMID="46">
				<isKnown>false</isKnown>
				<fogColor>1.0,1.0,1.0</fogColor>
				<skyColor>0.0,0.97917414,1.0</skyColor>
				<gravitationalMultiplier>50</gravitationalMultiplier>
				<orbitalDistance>186</orbitalDistance>
				<orbitalPhi>0</orbitalPhi>
				<rotationalPeriod>192000</rotationalPeriod>
				<atmosphereDensity>17</atmosphereDensity>
				<biomeIds>advancedrocketry:moon,advancedrocketry:moondark</biomeIds>
			</planet>
			<planet name="Sol-45: 1" DIMID="47">
				<isKnown>false</isKnown>
				<fogColor>1.0,1.0,1.0</fogColor>
				<skyColor>0.0,0.7169235,1.0</skyColor>
				<gravitationalMultiplier>49</gravitationalMultiplier>
				<orbitalDistance>175</orbitalDistance>
				<orbitalPhi>0</orbitalPhi>
				<rotationalPeriod>203996</rotationalPeriod>
				<atmosphereDensity>17</atmosphereDensity>
				<seaLevel>77</seaLevel>
				<biomeIds>advancedrocketry:moon,advancedrocketry:moondark</biomeIds>
				<oceanBlock>advancedrocketry:oxygenfluid</oceanBlock>
			</planet>
		</planet>
	</star>
	<star name="Proxima Centaurs" temp="200" x="-150" y="250" size="1.0" numPlanets="0" numGasGiants="0" >
		<planet name="Sol-58" DIMID="58">
			<isKnown>false</isKnown>
			<fogColor>1.0,1.0,1.0</fogColor>
			<skyColor>0.8,0.56137645,0.19278789</skyColor>
			<gravitationalMultiplier>130</gravitationalMultiplier>
			<orbitalDistance>87</orbitalDistance>
			<orbitalPhi>-2</orbitalPhi>
			<rotationalPeriod>10923</rotationalPeriod>
			<atmosphereDensity>137</atmosphereDensity>
			<seaLevel>58</seaLevel>
			<biomeIds>minecraft:deep_ocean,biomesoplenty:fungi_forest,minecraft:mutated_desert,minecraft:mutated_mesa_rock,minecraft:mutated_mesa_clear_rock,advancedrocketry:deepswamp,advancedrocketry:stormland</biomeIds>
			<planet name="Sol-58: 0" DIMID="59">
				<isKnown>false</isKnown>
				<fogColor>1.0,1.0,1.0</fogColor>
				<skyColor>0.023217559,0.8557693,1.0</skyColor>
				<gravitationalMultiplier>58</gravitationalMultiplier>
				<orbitalDistance>187</orbitalDistance>
				<orbitalPhi>0</orbitalPhi>
				<rotationalPeriod>123006</rotationalPeriod>
				<atmosphereDensity>35</atmosphereDensity>
				<biomeIds>biomesoplenty:undergarden,biomesoplenty:tropical_rainforest,minecraft:mutated_birch_forest,minecraft:jungle_hills,biomesoplenty:flower_island</biomeIds>
			</planet>
			<oceanBlock>minecraft:lava</oceanBlock>
		</planet>
		<planet name="Sol-60" DIMID="60">
			<isKnown>false</isKnown>
			<fogColor>1.0,1.0,1.0</fogColor>
			<skyColor>0.8,0.86968774,0.24943292</skyColor>
			<gravitationalMultiplier>130</gravitationalMultiplier>
			<orbitalDistance>81</orbitalDistance>
			<orbitalPhi>-9</orbitalPhi>
			<rotationalPeriod>10923</rotationalPeriod>
			<atmosphereDensity>126</atmosphereDensity>
			<biomeIds>minecraft:mushroom_island</biomeIds>
			<planet name="Sol-60: 0" DIMID="61">
				<isKnown>false</isKnown>
				<fogColor>1.0,1.0,1.0</fogColor>
				<skyColor>0.06493133,0.79645765,1.0</skyColor>
				<gravitationalMultiplier>77</gravitationalMultiplier>
				<orbitalDistance>155</orbitalDistance>
				<orbitalPhi>3</orbitalPhi>
				<rotationalPeriod>52570</rotationalPeriod>
				<atmosphereDensity>14</atmosphereDensity>
				<biomeIds>advancedrocketry:moon,advancedrocketry:moondark</biomeIds>
			</planet>
			<oceanBlock>minecraft:lava</oceanBlock>
		</planet>
		<planet name="Sol-62" DIMID="62">
			<isKnown>false</isKnown>
			<fogColor>1.0,1.0,1.0</fogColor>
			<skyColor>0.13321328,0.9468665,1.0</skyColor>
			<gravitationalMultiplier>128</gravitationalMultiplier>
			<orbitalDistance>176</orbitalDistance>
			<orbitalPhi>-2</orbitalPhi>
			<rotationalPeriod>11444</rotationalPeriod>
			<atmosphereDensity>43</atmosphereDensity>
			<biomeIds>minecraft:forest_hills,biomesoplenty:cherry_blossom_grove,advancedrocketry:oceanspires,minecraft:swampland,minecraft:mushroom_island_shore</biomeIds>
			<planet name="Sol-62: 0" DIMID="63">
				<isKnown>false</isKnown>
				<fogColor>1.0,1.0,1.0</fogColor>
				<skyColor>0.36483288,0.7694001,1.0</skyColor>
				<gravitationalMultiplier>44</gravitationalMultiplier>
				<orbitalDistance>125</orbitalDistance>
				<orbitalPhi>-5</orbitalPhi>
				<rotationalPeriod>281743</rotationalPeriod>
				<atmosphereDensity>26</atmosphereDensity>
				<biomeIds>minecraft:beaches,biomesoplenty:corrupted_sands,biomesoplenty:undergarden,biomesoplenty:highland,minecraft:mutated_birch_forest</biomeIds>
			</planet>
		</planet>
	</star>
	<star name="Magnis Vulpes" temp="70" x="-150" y="-250" size="1.0" numPlanets="0" numGasGiants="0" >
		<planet name="Sol-64" DIMID="64">
			<isKnown>false</isKnown>
			<fogColor>1.0,1.0,1.0</fogColor>
			<skyColor>0.8,0.57110727,0.0</skyColor>
			<gravitationalMultiplier>129</gravitationalMultiplier>
			<orbitalDistance>89</orbitalDistance>
			<orbitalPhi>-7</orbitalPhi>
			<rotationalPeriod>11180</rotationalPeriod>
			<atmosphereDensity>174</atmosphereDensity>
			<seaLevel>74</seaLevel>
			<biomeIds>advancedrocketry:hotdryrock,advancedrocketry:volcanic</biomeIds>
			<planet name="Sol-64: 0" DIMID="65">
				<isKnown>false</isKnown>
				<hasRings>true</hasRings>
				<ringColor>0.0,0.7636547,1.0</ringColor>
				<fogColor>1.0,1.0,1.0</fogColor>
				<skyColor>0.0,0.7636547,1.0</skyColor>
				<gravitationalMultiplier>87</gravitationalMultiplier>
				<orbitalDistance>196</orbitalDistance>
				<orbitalPhi>0</orbitalPhi>
				<rotationalPeriod>36446</rotationalPeriod>
				<atmosphereDensity>34</atmosphereDensity>
				<seaLevel>46</seaLevel>
				<biomeIds>minecraft:plains,minecraft:mutated_savanna,minecraft:swampland,biomesoplenty:redwood_forest_edge,minecraft:jungle_hills</biomeIds>
			</planet>
			<oceanBlock>minecraft:lava</oceanBlock>
		</planet>
		<planet name="Sol-66" DIMID="66">
			<isKnown>false</isKnown>
			<fogColor>1.0,1.0,1.0</fogColor>
			<skyColor>0.8,0.68804556,0.26009673</skyColor>
			<gravitationalMultiplier>116</gravitationalMultiplier>
			<orbitalDistance>88</orbitalDistance>
			<orbitalPhi>0</orbitalPhi>
			<rotationalPeriod>14984</rotationalPeriod>
			<atmosphereDensity>142</atmosphereDensity>
			<biomeIds>biomesoplenty:lush_desert,advancedrocketry:marsh,minecraft:desert_hills,biomesoplenty:bayou,minecraft:savanna_rock,advancedrocketry:deepswamp,advancedrocketry:stormland</biomeIds>
			<planet name="Sol-66: 0" DIMID="67">
				<isKnown>false</isKnown>
				<fogColor>1.0,1.0,1.0</fogColor>
				<skyColor>0.0,0.70617616,1.0</skyColor>
				<gravitationalMultiplier>77</gravitationalMultiplier>
				<orbitalDistance>180</orbitalDistance>
				<orbitalPhi>-2</orbitalPhi>
				<rotationalPeriod>52570</rotationalPeriod>
				<atmosphereDensity>26</atmosphereDensity>
				<biomeIds>biomesoplenty:steppe,minecraft:mutated_plains,advancedrocketry:oceanspires,minecraft:forest_hills,biomesoplenty:pasture</biomeIds>
			</planet>
			<planet name="Sol-66: 1" DIMID="68">
				<isKnown>false</isKnown>
				<fogColor>1.0,1.0,1.0</fogColor>
				<skyColor>0.17757946,0.5794595,1.0</skyColor>
				<gravitationalMultiplier>54</gravitationalMultiplier>
				<orbitalDistance>153</orbitalDistance>
				<orbitalPhi>2</orbitalPhi>
				<rotationalPeriod>152415</rotationalPeriod>
				<atmosphereDensity>30</atmosphereDensity>
				<biomeIds>minecraft:swampland,minecraft:plains,minecraft:mesa_clear_rock,biomesoplenty:shrubland,biomesoplenty:brushland</biomeIds>
			</planet>
			<oceanBlock>minecraft:lava</oceanBlock>
		</planet>
	</star>
	<star name="Ma-Roo" temp="200" x="50" y="-250" size="1.0" numPlanets="0" numGasGiants="0" >
		<planet name="Sol-81" DIMID="81">
			<isKnown>false</isKnown>
			<fogColor>1.0,1.0,1.0</fogColor>
			<skyColor>0.3699646,0.7664759,1.0</skyColor>
			<gravitationalMultiplier>96</gravitationalMultiplier>
			<orbitalDistance>107</orbitalDistance>
			<orbitalPhi>3</orbitalPhi>
			<rotationalPeriod>27126</rotationalPeriod>
			<atmosphereDensity>7</atmosphereDensity>
			<biomeIds>advancedrocketry:moon,advancedrocketry:moondark</biomeIds>
		</planet>
		<planet name="Sol-69" DIMID="69">
			<isKnown>false</isKnown>
			<fogColor>1.0,1.0,1.0</fogColor>
			<skyColor>0.8,0.8609661,0.0</skyColor>
			<gravitationalMultiplier>116</gravitationalMultiplier>
			<orbitalDistance>38</orbitalDistance>
			<orbitalPhi>-7</orbitalPhi>
			<rotationalPeriod>14984</rotationalPeriod>
			<atmosphereDensity>165</atmosphereDensity>
			<biomeIds>advancedrocketry:hotdryrock,advancedrocketry:volcanic</biomeIds>
			<planet name="Sol-69: 0" DIMID="70">
				<isKnown>false</isKnown>
				<fogColor>1.0,1.0,1.0</fogColor>
				<skyColor>0.3195545,0.9579414,1.0</skyColor>
				<gravitationalMultiplier>50</gravitationalMultiplier>
				<orbitalDistance>124</orbitalDistance>
				<orbitalPhi>5</orbitalPhi>
				<rotationalPeriod>192000</rotationalPeriod>
				<atmosphereDensity>16</atmosphereDensity>
				<biomeIds>advancedrocketry:moon,advancedrocketry:moondark</biomeIds>
			</planet>
			<oceanBlock>minecraft:lava</oceanBlock>
		</planet>
		<planet name="Sol-71" DIMID="71">
			<isKnown>false</isKnown>
			<fogColor>1.0,1.0,1.0</fogColor>
			<skyColor>0.8,0.80006814,1.0</skyColor>
			<gravitationalMultiplier>109</gravitationalMultiplier>
			<orbitalDistance>138</orbitalDistance>
			<orbitalPhi>-5</orbitalPhi>
			<rotationalPeriod>18532</rotationalPeriod>
			<atmosphereDensity>91</atmosphereDensity>
			<biomeIds>advancedrocketry:crystalchasms</biomeIds>
		</planet>
		<planet name="Sol-72" DIMID="72">
			<isKnown>false</isKnown>
			<fogColor>1.0,1.0,1.0</fogColor>
			<skyColor>0.28760743,0.7436794,1.0</skyColor>
			<gravitationalMultiplier>126</gravitationalMultiplier>
			<orbitalDistance>126</orbitalDistance>
			<orbitalPhi>-3</orbitalPhi>
			<rotationalPeriod>11997</rotationalPeriod>
			<atmosphereDensity>11</atmosphereDensity>
			<seaLevel>68</seaLevel>
			<biomeIds>advancedrocketry:moon,advancedrocketry:moondark</biomeIds>
			<planet name="Sol-72: 0" DIMID="73">
				<isKnown>false</isKnown>
				<fogColor>1.0,1.0,1.0</fogColor>
				<skyColor>0.056127667,0.77877927,1.0</skyColor>
				<gravitationalMultiplier>60</gravitationalMultiplier>
				<orbitalDistance>162</orbitalDistance>
				<orbitalPhi>-3</orbitalPhi>
				<rotationalPeriod>111111</rotationalPeriod>
				<atmosphereDensity>23</atmosphereDensity>
				<seaLevel>56</seaLevel>
				<biomeIds>advancedrocketry:moon,advancedrocketry:moondark</biomeIds>
			</planet>
			<planet name="Sol-72: 1" DIMID="74">
				<isKnown>false</isKnown>
				<fogColor>1.0,1.0,1.0</fogColor>
				<skyColor>0.0,0.9212967,1.0</skyColor>
				<gravitationalMultiplier>43</gravitationalMultiplier>
				<orbitalDistance>195</orbitalDistance>
				<orbitalPhi>-3</orbitalPhi>
				<rotationalPeriod>301860</rotationalPeriod>
				<atmosphereDensity>28</atmosphereDensity>
				<biomeIds>biomesoplenty:mountain_foothills,biomesoplenty:sacred_springs,biomesoplenty:visceral_heap,biomesoplenty:oasis,biomesoplenty:corrupted_sands</biomeIds>
			</planet>
		</planet>
		<planet name="Sol-75" DIMID="75">
			<isKnown>false</isKnown>
			<fogColor>1.0,1.0,1.0</fogColor>
			<skyColor>0.8,0.51066244,0.23845935</skyColor>
			<gravitationalMultiplier>130</gravitationalMultiplier>
			<orbitalDistance>125</orbitalDistance>
			<orbitalPhi>3</orbitalPhi>
			<rotationalPeriod>10923</rotationalPeriod>
			<atmosphereDensity>170</atmosphereDensity>
			<biomeIds>minecraft:desert_hills</biomeIds>
			<planet name="Sol-75: 0" DIMID="76">
				<isKnown>false</isKnown>
				<fogColor>1.0,1.0,1.0</fogColor>
				<skyColor>0.0,0.57120854,1.0</skyColor>
				<gravitationalMultiplier>85</gravitationalMultiplier>
				<orbitalDistance>188</orbitalDistance>
				<orbitalPhi>0</orbitalPhi>
				<rotationalPeriod>39079</rotationalPeriod>
				<atmosphereDensity>15</atmosphereDensity>
				<biomeIds>advancedrocketry:moon,advancedrocketry:moondark</biomeIds>
			</planet>
			<oceanBlock>minecraft:lava</oceanBlock>
		</planet>
		<planet name="Sol-77" DIMID="77">
			<isKnown>false</isKnown>
			<fogColor>1.0,1.0,1.0</fogColor>
			<skyColor>0.8,0.99428916,0.0</skyColor>
			<gravitationalMultiplier>130</gravitationalMultiplier>
			<orbitalDistance>9</orbitalDistance>
			<orbitalPhi>-4</orbitalPhi>
			<rotationalPeriod>10923</rotationalPeriod>
			<atmosphereDensity>108</atmosphereDensity>
			<biomeIds>advancedrocketry:hotdryrock,advancedrocketry:volcanic</biomeIds>
			<planet name="Sol-77: 2" DIMID="80">
				<isKnown>false</isKnown>
				<fogColor>1.0,1.0,1.0</fogColor>
				<skyColor>0.0,0.52810574,1.0</skyColor>
				<gravitationalMultiplier>50</gravitationalMultiplier>
				<orbitalDistance>190</orbitalDistance>
				<orbitalPhi>0</orbitalPhi>
				<rotationalPeriod>192000</rotationalPeriod>
				<atmosphereDensity>24</atmosphereDensity>
				<biomeIds>advancedrocketry:moon,advancedrocketry:moondark</biomeIds>
			</planet>
			<planet name="Sol-77: 0" DIMID="78">
				<isKnown>false</isKnown>
				<fogColor>1.0,1.0,1.0</fogColor>
				<skyColor>0.3725093,0.80194247,1.0</skyColor>
				<gravitationalMultiplier>41</gravitationalMultiplier>
				<orbitalDistance>127</orbitalDistance>
				<orbitalPhi>-1</orbitalPhi>
				<rotationalPeriod>348224</rotationalPeriod>
				<atmosphereDensity>30</atmosphereDensity>
				<biomeIds>minecraft:plains,biomesoplenty:redwood_forest_edge,minecraft:jungle_edge,minecraft:mutated_roofed_forest,minecraft:swampland</biomeIds>
			</planet>
			<planet name="Sol-77: 1" DIMID="79">
				<isKnown>false</isKnown>
				<fogColor>1.0,1.0,1.0</fogColor>
				<skyColor>0.0,0.79657376,1.0</skyColor>
				<gravitationalMultiplier>55</gravitationalMultiplier>
				<orbitalDistance>172</orbitalDistance>
				<orbitalPhi>-6</orbitalPhi>
				<rotationalPeriod>144252</rotationalPeriod>
				<atmosphereDensity>18</atmosphereDensity>
				<biomeIds>advancedrocketry:moon,advancedrocketry:moondark</biomeIds>
			</planet>
			<oceanBlock>minecraft:lava</oceanBlock>
		</planet>
	</star>
	<star name="Alykitt" temp="120" x="75" y="200" size="1.0" numPlanets="0" numGasGiants="0" >
		<planet name="Sol-82" DIMID="82">
			<isKnown>false</isKnown>
			<GasGiant>true</GasGiant>
			<gas>nitrogen</gas>
			<gas>oxygen</gas>
			<gas>hydrogen</gas>
			<fogColor>1.0,1.0,1.0</fogColor>
			<skyColor>1.0,1.0,1.0</skyColor>
			<gravitationalMultiplier>111</gravitationalMultiplier>
			<orbitalDistance>200</orbitalDistance>
			<orbitalPhi>0</orbitalPhi>
			<rotationalPeriod>24000</rotationalPeriod>
			<atmosphereDensity>138</atmosphereDensity>
			<planet name="Sol-82: 0" DIMID="83">
				<isKnown>false</isKnown>
				<fogColor>1.0,1.0,1.0</fogColor>
				<skyColor>0.17369306,0.9463434,1.0</skyColor>
				<gravitationalMultiplier>58</gravitationalMultiplier>
				<orbitalDistance>140</orbitalDistance>
				<orbitalPhi>3</orbitalPhi>
				<rotationalPeriod>123006</rotationalPeriod>
				<atmosphereDensity>20</atmosphereDensity>
				<biomeIds>advancedrocketry:moon,advancedrocketry:moondark</biomeIds>
			</planet>
			<planet name="Sol-82: 1" DIMID="84">
				<isKnown>false</isKnown>
				<fogColor>1.0,1.0,1.0</fogColor>
				<skyColor>0.0,0.8626119,1.0</skyColor>
				<gravitationalMultiplier>41</gravitationalMultiplier>
				<orbitalDistance>195</orbitalDistance>
				<orbitalPhi>1</orbitalPhi>
				<rotationalPeriod>348224</rotationalPeriod>
				<atmosphereDensity>27</atmosphereDensity>
				<biomeIds>biomesoplenty:grove,advancedrocketry:oceanspires,minecraft:mutated_savanna,minecraft:mesa_clear_rock,biomesoplenty:cherry_blossom_grove</biomeIds>
			</planet>
		</planet>
		<planet name="Sol-85" DIMID="85">
			<isKnown>false</isKnown>
			<fogColor>1.0,1.0,1.0</fogColor>
			<skyColor>0.8,0.9437721,0.0</skyColor>
			<gravitationalMultiplier>98</gravitationalMultiplier>
			<orbitalDistance>70</orbitalDistance>
			<orbitalPhi>-1</orbitalPhi>
			<rotationalPeriod>25499</rotationalPeriod>
			<atmosphereDensity>200</atmosphereDensity>
			<biomeIds>advancedrocketry:hotdryrock,advancedrocketry:volcanic</biomeIds>
			<oceanBlock>minecraft:lava</oceanBlock>
		</planet>
		<planet name="Sol-86" DIMID="86">
			<isKnown>false</isKnown>
			<fogColor>1.0,1.0,1.0</fogColor>
			<skyColor>0.8,0.7459961,0.7914127</skyColor>
			<gravitationalMultiplier>104</gravitationalMultiplier>
			<orbitalDistance>166</orbitalDistance>
			<orbitalPhi>-2</orbitalPhi>
			<rotationalPeriod>20150</rotationalPeriod>
			<atmosphereDensity>147</atmosphereDensity>
			<biomeIds>minecraft:jungle_edge,biomesoplenty:quagmire,minecraft:mutated_redwood_taiga,minecraft:extreme_hills_with_trees,minecraft:mesa_clear_rock,advancedrocketry:deepswamp,advancedrocketry:stormland</biomeIds>
			<planet name="Sol-86: 0" DIMID="87">
				<isKnown>false</isKnown>
				<fogColor>1.0,1.0,1.0</fogColor>
				<skyColor>0.40599436,0.6714554,1.0</skyColor>
				<gravitationalMultiplier>37</gravitationalMultiplier>
				<orbitalDistance>120</orbitalDistance>
				<orbitalPhi>-1</orbitalPhi>
				<rotationalPeriod>473812</rotationalPeriod>
				<atmosphereDensity>30</atmosphereDensity>
				<biomeIds>minecraft:mutated_savanna,biomesoplenty:ominous_woods,minecraft:mutated_mesa_clear_rock,biomesoplenty:mountain_foothills,minecraft:mutated_savanna_rock</biomeIds>
			</planet>
			<planet name="Sol-86: 1" DIMID="88">
				<isKnown>false</isKnown>
				<fogColor>1.0,1.0,1.0</fogColor>
				<skyColor>0.010384321,0.7379107,1.0</skyColor>
				<gravitationalMultiplier>32</gravitationalMultiplier>
				<orbitalDistance>191</orbitalDistance>
				<orbitalPhi>0</orbitalPhi>
				<rotationalPeriod>732421</rotationalPeriod>
				<atmosphereDensity>37</atmosphereDensity>
				<biomeIds>minecraft:savanna_rock,biomesoplenty:moor,minecraft:jungle_hills,minecraft:deep_ocean,minecraft:mutated_savanna</biomeIds>
			</planet>
			<planet name="Sol-86: 2" DIMID="89">
				<isKnown>false</isKnown>
				<fogColor>1.0,1.0,1.0</fogColor>
				<skyColor>0.2470792,0.6285957,1.0</skyColor>
				<gravitationalMultiplier>39</gravitationalMultiplier>
				<orbitalDistance>150</orbitalDistance>
				<orbitalPhi>-4</orbitalPhi>
				<rotationalPeriod>404592</rotationalPeriod>
				<atmosphereDensity>36</atmosphereDensity>
				<seaLevel>45</seaLevel>
				<biomeIds>minecraft:mutated_desert,biomesoplenty:cherry_blossom_grove,minecraft:mesa_rock,minecraft:mutated_savanna_rock,biomesoplenty:grove</biomeIds>
			</planet>
		</planet>
		<planet name="Sol-90" DIMID="90">
			<isKnown>false</isKnown>
			<fogColor>1.0,1.0,1.0</fogColor>
			<skyColor>0.0,0.5889629,1.0</skyColor>
			<gravitationalMultiplier>104</gravitationalMultiplier>
			<orbitalDistance>158</orbitalDistance>
			<orbitalPhi>1</orbitalPhi>
			<rotationalPeriod>20732</rotationalPeriod>
			<atmosphereDensity>0</atmosphereDensity>
			<biomeIds>advancedrocketry:moon,advancedrocketry:moondark</biomeIds>
		</planet>
	</star>
</galaxy>